MANIFEST.in
README.rst
requirements.txt
setup.py
simple_rest/__init__.py
simple_rest.egg-info/PKG-INFO
simple_rest.egg-info/SOURCES.txt
simple_rest.egg-info/dependency_links.txt
simple_rest.egg-info/requires.txt
simple_rest.egg-info/top_level.txt