Metadata-Version: 1.0
Name: simple-rest
Version: 0.0.3
Summary: very simple rest client framework
Home-page: https://bitbucket.org/afriemann/simple_rest.git
Author: Aljosha Friemann
Author-email: aljosha.friemann@gmail.com
License: UNKNOWN
Platform: UNKNOWN
